artifacts/@openzeppelin/contracts/access/AccessControl.sol/AccessControl.json
artifacts/@openzeppelin/contracts/access/IAccessControl.sol/IAccessControl.json
artifacts/@openzeppelin/contracts/access/Ownable.sol/Ownable.json
artifacts/@openzeppelin/contracts/governance/TimelockController.sol/TimelockController.json
artifacts/@openzeppelin/contracts/governance/utils/IVotes.sol/IVotes.json
artifacts/@openzeppelin/contracts/governance/utils/Votes.sol/Votes.json
artifacts/@openzeppelin/contracts/interfaces/IERC5267.sol/IERC5267.json
artifacts/@openzeppelin/contracts/interfaces/IERC5805.sol/IERC5805.json
artifacts/@openzeppelin/contracts/interfaces/IERC6372.sol/IERC6372.json
artifacts/@openzeppelin/contracts/interfaces/draft-IERC6093.sol/IERC1155Errors.json
artifacts/@openzeppelin/contracts/interfaces/draft-IERC6093.sol/IERC20Errors.json
artifacts/@openzeppelin/contracts/interfaces/draft-IERC6093.sol/IERC721Errors.json
artifacts/@openzeppelin/contracts/proxy/ERC1967/ERC1967Proxy.sol/ERC1967Proxy.json
artifacts/@openzeppelin/contracts/proxy/ERC1967/ERC1967Utils.sol/ERC1967Utils.json
artifacts/@openzeppelin/contracts/proxy/Proxy.sol/Proxy.json
artifacts/@openzeppelin/contracts/proxy/beacon/IBeacon.sol/IBeacon.json
artifacts/@openzeppelin/contracts/token/ERC1155/IERC1155Receiver.sol/IERC1155Receiver.json
artifacts/@openzeppelin/contracts/token/ERC1155/utils/ERC1155Holder.sol/ERC1155Holder.json
artifacts/@openzeppelin/contracts/token/ERC20/ERC20.sol/ERC20.json
artifacts/@openzeppelin/contracts/token/ERC20/IERC20.sol/IERC20.json
artifacts/@openzeppelin/contracts/token/ERC20/extensions/ERC20Permit.sol/ERC20Permit.json
artifacts/@openzeppelin/contracts/token/ERC20/extensions/ERC20Votes.sol/ERC20Votes.json
artifacts/@openzeppelin/contracts/token/ERC20/extensions/ERC20Wrapper.sol/ERC20Wrapper.json
artifacts/@openzeppelin/contracts/token/ERC20/extensions/IERC20Metadata.sol/IERC20Metadata.json
artifacts/build-info/0e123c5e0041b344dd11789994105fae.json
artifacts/build-info/dbd6d8494458dfc95c739eb724294bd6.json
human_protocol_sdk-6.0.0.dist-info/LICENSE
human_protocol_sdk-6.0.0.dist-info/METADATA
human_protocol_sdk-6.0.0.dist-info/WHEEL
human_protocol_sdk-6.0.0.dist-info/top_level.txt
human_protocol_sdk-6.0.0.dist-info/zip-safe
human_protocol_sdk-6.0.0.dist-info/RECORD
